README.md
setup.py
sweetcase/__init__.py
sweetcase/__version__.py
sweetcase/case.py
sweetcase/default.py
sweetcase/exceptions.py
sweetcase/switch.py
sweetcase/utils.py
sweetcase.egg-info/PKG-INFO
sweetcase.egg-info/SOURCES.txt
sweetcase.egg-info/dependency_links.txt
sweetcase.egg-info/top_level.txt
tests/__init__.py
tests/test_arguments.py
tests/test_basic.py
tests/test_break.py
tests/test_complex.py
tests/test_goto.py
tests/test_multicase.py
tests/test_multiline_functions.py
tests/test_regex.py