Metadata-Version: 2.1
Name: sweetcase
Version: 0.0.5
Summary: Simple and light-weight module allowing the use of a switch-case alike syntax in python
Home-page: https://github.com/niryarden/sweetcase
Author: Nir Yarden
Author-email: niryar@gmail.com
License: UNKNOWN
Platform: UNKNOWN
Classifier: Programming Language :: Python :: 3
Classifier: License :: OSI Approved :: MIT License
Classifier: Operating System :: OS Independent
Classifier: Development Status :: 4 - Beta
Classifier: Intended Audience :: Developers
Requires-Python: >=3.0
